README.md
setup.py
batch_retry/__init__.py
batch_retry/batch_retry.py
batch_retry/kinesis_processor.py
batch_retry.egg-info/PKG-INFO
batch_retry.egg-info/SOURCES.txt
batch_retry.egg-info/dependency_links.txt
batch_retry.egg-info/requires.txt
batch_retry.egg-info/top_level.txt