Metadata-Version: 1.0
Name: batch-retry
Version: 0.0.2
Summary: Batch send data with retries and exponential backoff
Home-page: https://github.com/envato/batch_retry
Author: probinson
Author-email: patrick.robinson@envato.com
License: MIT
Platform: UNKNOWN
